hgq/__init__.py
hgq/_version.py
hgq/config/__init__.py
hgq/config/layer.py
hgq/config/quantizer.py
hgq/constraints/__init__.py
hgq/layers/__init__.py
hgq/layers/activation.py
hgq/layers/batch_normalization.py
hgq/layers/conv.py
hgq/layers/einsum_dense_batchnorm.py
hgq/layers/linformer_attention.py
hgq/layers/multi_head_attention.py
hgq/layers/pooling.py
hgq/layers/softmax.py
hgq/layers/core/__init__.py
hgq/layers/core/base.py
hgq/layers/core/dense.py
hgq/layers/core/einsum_dense.py
hgq/layers/ops/__init__.py
hgq/layers/ops/accum.py
hgq/layers/ops/einsum.py
hgq/layers/ops/merge.py
hgq/layers/rnn/__init__.py
hgq/layers/rnn/gru.py
hgq/layers/rnn/simple_rnn.py
hgq/layers/table/__init__.py
hgq/layers/table/conv.py
hgq/layers/table/dense.py
hgq/quantizer/__init__.py
hgq/quantizer/config.py
hgq/quantizer/quantizer.py
hgq/quantizer/internal/__init__.py
hgq/quantizer/internal/base.py
hgq/quantizer/internal/fixed_point_quantizer.py
hgq/quantizer/internal/float_point_quantizer.py
hgq/regularizers/__init__.py
hgq/utils/__init__.py
hgq/utils/dataset.py
hgq/utils/minmax_trace.py
hgq/utils/misc.py
hgq/utils/singleton.py
hgq/utils/sugar/__init__.py
hgq/utils/sugar/beta_pid.py
hgq/utils/sugar/beta_scheduler.py
hgq/utils/sugar/early_stopping_ebops.py
hgq/utils/sugar/ebops.py
hgq/utils/sugar/pareto.py
hgq/utils/sugar/pbar.py
hgq2-0.1.5.dist-info/licenses/LICENSE
qkeras/__init__.py
qkeras/initializers/__init__.py
qkeras/initializers/initializer.py
qkeras/qlayers/__init__.py
qkeras/qlayers/__init__.pyi
qkeras/quantizers/__init__.py
qkeras/quantizers/frozen_quantizer.py
qkeras/quantizers/quantized_bits.py
qkeras/quantizers/utils.py
hgq2-0.1.5.dist-info/METADATA
hgq2-0.1.5.dist-info/WHEEL
hgq2-0.1.5.dist-info/top_level.txt
hgq2-0.1.5.dist-info/RECORD
