Metadata-Version: 2.4
Name: hgq2
Version: 0.1.5
Summary: High Granularity Quantization 2
Author-email: Chang Sun <chsun@cern.ch>
License: GNU Lesser General Public License v3 (LGPLv3)
Project-URL: repository, https://github.com/calad0i/HGQ2
Keywords: hls4ml,keras,qkeras,quantization
Classifier: Development Status :: 4 - Beta
Classifier: License :: OSI Approved :: GNU Lesser General Public License v3 (LGPLv3)
Classifier: Operating System :: OS Independent
Classifier: Programming Language :: Python :: 3 :: Only
Classifier: Programming Language :: Python :: 3.10
Classifier: Programming Language :: Python :: 3.11
Classifier: Programming Language :: Python :: 3.12
Classifier: Programming Language :: Python :: 3.13
Requires-Python: >=3.10
License-File: LICENSE
Requires-Dist: keras>=3.11
Requires-Dist: quantizers>=1.2.2
Requires-Dist: tqdm
Provides-Extra: docs
Requires-Dist: myst-parser; extra == "docs"
Requires-Dist: pyparsing; extra == "docs"
Requires-Dist: sphinx; extra == "docs"
Requires-Dist: sphinx-rtd-theme; extra == "docs"
Provides-Extra: test
Requires-Dist: da4ml>=0.3; extra == "test"
Requires-Dist: hls4ml>=1.2; extra == "test"
Requires-Dist: jax>=0.4.20; extra == "test"
Requires-Dist: jaxlib>=0.4.20; extra == "test"
Requires-Dist: keras>=3; extra == "test"
Requires-Dist: numpy>=1.23; extra == "test"
Requires-Dist: pyparsing; extra == "test"
Requires-Dist: pytest>=7; extra == "test"
Requires-Dist: pytest-cov>=4; extra == "test"
Requires-Dist: pytest-env; extra == "test"
Requires-Dist: pytest-sugar; extra == "test"
Requires-Dist: pytest-xdist>=3.3; extra == "test"
Dynamic: license-file
